uncloud/__init__.py
uncloud/__main__.py
uncloud/download.py
uncloud/extract.py
uncloud/uncloud.py
uncloud-0.0.1.dist-info/METADATA
uncloud-0.0.1.dist-info/WHEEL
uncloud-0.0.1.dist-info/entry_points.txt
uncloud-0.0.1.dist-info/licenses/LICENSE
uncloud-0.0.1.dist-info/RECORD
