Metadata-Version: 2.4
Name: uncloud
Version: 0.0.1
Summary: Download a public archive file from popular cloud storage services such as Dropbox, Google Drive, and OneDrive.
Project-URL: Repository, https://github.com/imyizhang/uncloud
Author-email: Yi Zhang <yizhang.dev@gmail.com>
License-Expression: MIT
License-File: LICENSE
Requires-Python: >=3.12
Requires-Dist: playwright
Requires-Dist: requests
Requires-Dist: tqdm
Provides-Extra: dev
Requires-Dist: ruff; extra == 'dev'
